[
    {
        "id": "abc1",
        "title": "Oppenheimer ✨",
        "date": "12 Jan 2023",
        "skills": "Pinning in Rust",
        "endorsers": ["Vaibhav", "Yash", "Tejas"],
        "status": "Atomic",
        "endorsements": [
            {
                "id": 1,
                "name": "Vaibhav",
                "description": "Lorem ipsum dolor sit amet consectetur. Lacus consequat non porttitor faucibus. Mattis nec felis sagittis justo id volutpat."
            },
            {
                "id": 2,
                "name": "Yash",
                "description": "Lorem ipsum dolor sit amet consectetur. Lacus consequat non porttitor faucibus. Mattis nec felis sagittis justo id volutpat. Et ut non semper quam a consectetur Et ut non semper quam a consectetur."
            },
            {
                "id": 3,
                "name": "Tejas",
                "description": "Lorem ipsum dolor sit amet consectetur. Lacus consequat non porttitor faucibus. Mattis nec felis sagittis justo id volutpat. Et ut non semper quam a consectetur Et ut non semper quam a consectetur."
            }
        ]
    },
    {
        "id": "abc2",
        "title": "Oppenheimer ✨",
        "date": "12 Jan 2023",
        "skills": "Pinning in Rust",
        "endorsers": ["Vaibhav", "Yash", "Tejas"],
        "status": "Atomic",
        "endorsements": [
            {
                "id": 1,
                "name": "Vaibhav",
                "description": "Lorem ipsum dolor sit amet consectetur. Lacus consequat non porttitor faucibus. Mattis nec felis sagittis justo id volutpat. Et ut non semper quam a consectetur Et ut non semper quam a consectetur."
            },
            {
                "id": 2,
                "name": "Yash",
                "description": "Lorem ipsum dolor sit amet consectetur. Lacus consequat non porttitor faucibus. Mattis nec felis sagittis justo id volutpat."
            },
            {
                "id": 3,
                "name": "Tejas",
                "description": "Lorem ipsum dolor sit amet consectetur. Lacus consequat non porttitor faucibus. Mattis nec felis sagittis justo id volutpat. Et ut non semper quam a consectetur Et ut non semper quam a consectetur."
            }
        ]
    }
]
